obhavo/__init__.py
obhavo/main.py
ObHavoUz-1.0.dist-info/METADATA
ObHavoUz-1.0.dist-info/WHEEL
ObHavoUz-1.0.dist-info/top_level.txt
ObHavoUz-1.0.dist-info/RECORD
