Metadata-Version: 2.1
Name: ObHavoUz
Version: 1.0
Summary: ObHavoUz
Home-page: https://github.com/bultakov/obhavouz
Author: Bultakov Ibrohim
Author-email: bii23.uz@gmail.com
Classifier: Programming Language :: Python :: 3
Classifier: License :: OSI Approved :: MIT License
Classifier: Operating System :: OS Independent
Requires-Dist: aiohttp
Requires-Dist: bs4
